{
  "file_path": "D:\\Code\\OCR\\assets\\後端.jpg",
  "timestamp": 1761960995,
  "total_pages": 1,
  "pages": [
    {
      "page_number": 1,
      "page_text": "本資料\n中文姓名 高立樂 羅馬拼音 KAO LI LEX\n生日 1994/1/1 年齡 30\n居住地區 新北市 汐止區 性用 男性\n汽機車駕照蓄持有 兵役\n台灣 台灣簽證\n就業狀態 在國中 預定可到園 錄取後1個月以内\n語言程度\n語言 相關證照名稱 椒別栽分數 取得年月 顧問評價\n日文 JLPT N2 2020/12 (B)初級商業程度\n英文 TOEIC 8009 2019/08 (B)初級商業程度\n[N] 母語程度·【A] 海南程度·[B] 初級商業梯度·【C】 日菜蜜話程度· 【D】 糖單點呼程度\n教育背景\n學位 開始年月 結束年月 現況\n國立東華大學 資訊管理學系 2017/09 2019/05 出著\n學士 國立彰化師範大學 數學系 2012/09 2016/06\n電腦技能\nOffice 能力\nWord 高級(文書製作/版画編排+圖表/圖形製作插入+樣藍製作/郵件合併列印)\nExcel 高級(文書製作/版面編排+圖表/圖形製作插入+標籤製作/郵件合併列印)\nPowerPoint 高級(文書製作/版面編排+儀表/圖形製作插入+標籤製作/郵件合併列印)\nNode.js (Passed Linkedin Skill Assessment) . Golang (Passed Linkedin Skill Assessment) · 後端開發與框架:\nPython/Pytorch . Socket Programming . gRPC\n其他 ·資料庫與資料存儲:MySQL/MariaDB · Dynamodb - Redis\n· 容器化與部署:Docker 、 Serverless\n· 網路興通訊:TCP/UDP Socket · Unix Socket\n其他證照 · 技能 · 資格\n其他證照 · 技能 · 資格名稱 取得年月\nAWS認證的系統操作管理員-助理級認證 2020/09\nAWS認證的開發人員-助理級認證 2021/01\nAWS認證的解決方案號講師-助理級認證 2021/03\n1",
      "formatted_text": "姓名: 高立樂\n\n本資料\n中文姓名 高立樂 羅馬拼音 KAO LI LEX\n生日 1994/1/1 年齡 30\n居住地區 新北市 汐止區 性用 男性\n汽機車駕照蓄持有 兵役\n台灣 台灣簽證\n就業狀態 在國中 預定可到園 錄取後1個月以内\n語言程度\n語言 相關證照名稱 椒別栽分數 取得年月 顧問評價\n日文 JLPT N2 2020/12 (B)初級商業程度\n英文 TOEIC 8009 2019/08 (B)初級商業程度\n[N] 母語程度·【A] 海南程度·[B] 初級商業梯度·【C】 日菜蜜話程度· 【D】 糖單點呼程度\n教育背景\n學位 開始年月 結束年月 現況\n國立東華大學 資訊管理學系 2017/09 2019/05 出著\n學士 國立彰化師範大學 數學系 2012/09 2016/06\n電腦技能\nOffice 能力\nWord 高級(文書製作/版画編排+圖表/圖形製作插入+樣藍製作/郵件合併列印)\nExcel 高級(文書製作/版面編排+圖表/圖形製作插入+標籤製作/郵件合併列印)\nPowerPoint 高級(文書製作/版面編排+儀表/圖形製作插入+標籤製作/郵件合併列印)\nNode.js (Passed Linkedin Skill Assessment) . Golang (Passed Linkedin Skill Assessment) · 後端開發與框架:\nPython/Pytorch . Socket Programming . gRPC\n其他 ·資料庫與資料存儲:MySQL/MariaDB · Dynamodb - Redis\n· 容器化與部署:Docker 、 Serverless\n· 網路興通訊:TCP/UDP Socket · Unix Socket\n其他證照 · 技能 · 資格\n其他證照 · 技能 · 資格名稱 取得年月\nAWS認證的系統操作管理員-助理級認證 2020/09\nAWS認證的開發人員-助理級認證 2021/01\nAWS認證的解決方案號講師-助理級認證 2021/03\n1",
      "compact_contact": {
        "姓名": "高立樂",
        "手機": "",
        "Email": ""
      },
      "total_lines": 79
    }
  ]
}